algomancy_content/__init__.py
algomancy_content/backend/__init__.py
algomancy_content/backend/placeholderalgorithmtemplate.py
algomancy_content/backend/placeholderetlfactory.py
algomancy_content/backend/placeholderinputconfig.py
algomancy_content/backend/placeholderkpitemplate.py
algomancy_content/librarymanager.py
algomancy_content/pages/__init__.py
algomancy_content/pages/page.py
algomancy_content/pages/placeholdercomparepage.py
algomancy_content/pages/placeholderdatapage.py
algomancy_content/pages/placeholderscenariopage.py
algomancy_content/pages/showcasehomepage.py
algomancy_content/pages/standarddatapage.py
algomancy_content/pages/standardhomepage.py
algomancy_content/pages/standardoverviewpage.py
algomancy_content/py.typed
algomancy_content-0.3.18.dist-info/WHEEL
algomancy_content-0.3.18.dist-info/METADATA
algomancy_content-0.3.18.dist-info/RECORD
