Metadata-Version: 2.3
Name: algomancy-content
Version: 0.3.18
Summary: Placeholder content for quick start to the Algomancy library
Author: Pepijn Wissing
Author-email: Pepijn Wissing <Wsg@cqm.nl>
Requires-Dist: algomancy-data
Requires-Dist: algomancy-scenario
Requires-Dist: dash
Requires-Dist: dash-bootstrap-components
Requires-Dist: dash-daq
Requires-Dist: pandas
Requires-Python: >=3.14
